kleur/__init__.py
kleur/cli/__init__.py
kleur/cli/palette_gen.py
kleur/cli/shades_gen.py
kleur/color.py
kleur/formatting.py
kleur/palettes.py
kleur/py.typed
kleur-2.0.9.dist-info/WHEEL
kleur-2.0.9.dist-info/entry_points.txt
kleur-2.0.9.dist-info/METADATA
kleur-2.0.9.dist-info/RECORD
