Metadata-Version: 2.4
Name: kleur
Version: 2.0.9
Summary: Color shades generator
Keywords: color shades generator,cli utility
Author: Huib Piguillet
Author-email: Huib Piguillet <huib@proton.me>
License-Expression: MIT
Classifier: Intended Audience :: Developers
Classifier: Topic :: Utilities
Classifier: Programming Language :: Python :: 3
Classifier: Programming Language :: Python :: 3.14
Classifier: Programming Language :: Python :: 3 :: Only
Requires-Dist: hsluv
Requires-Dist: based-utils
Requires-Python: >=3.14
Project-URL: Github, https://github.com/githuib/kleur
Project-URL: PyPI, https://pypi.org/project/kleur/
